<?xml version="1.0" encoding="UTF-8"?>
<odoo>
    <data>
        <record id="view_op_student_inherit_discipline" model="ir.ui.view">
            <field name="name">op.student.form</field>
            <field name="model">op.student</field>
            <field name="type">form</field>
            <field name="inherit_id" ref="openeducat_core.view_op_student_form"/>
            <field name="arch" type="xml">
                <xpath expr="//notebook" position="inside">
                    <page name="discipline" string="Discipline">
                        <group>
                            <field name="discipline_score"/>
                        </group>
                        <field name="discipline_ids" readonly="1">
                            <tree string="Discipline Details">
                                <field name="misbehaviour_category_id"/>
                                <field name="misbehaviour_type"/>
                                <button string="Submit Letter"
                                        groups="openeducat_core.group_op_back_office_admin"
                                        type="object"
                                        name="submit_apology_letter"/>
                            </tree>
                        </field>
                    </page>
                </xpath>
            </field>
        </record>
    </data>
</odoo>
